LICENSE
MANIFEST.in
README.md
setup.py
devpi_slack/__init__.py
devpi_slack/main.py
devpi_slack.egg-info/PKG-INFO
devpi_slack.egg-info/SOURCES.txt
devpi_slack.egg-info/dependency_links.txt
devpi_slack.egg-info/entry_points.txt
devpi_slack.egg-info/requires.txt
devpi_slack.egg-info/top_level.txt