Metadata-Version: 2.1
Name: devpi-slack
Version: 0.1.4
Summary: Devpi plugin for sending Slack channel notifications
Home-page: http://github.com/innoteq/devpi-slack
Author: Max Arnold
Author-email: arnold.maxim@gmail.com
License: BSD
Keywords: devpi slack notification
Platform: any
Classifier: Development Status :: 3 - Alpha
Classifier: Intended Audience :: System Administrators
Classifier: License :: OSI Approved :: BSD License
Classifier: Topic :: Software Development :: Libraries :: Python Modules
Classifier: Topic :: Internet
License-File: LICENSE
